XlsxLibrary/__init__.py
XlsxLibrary/version.py
robotframework_xlsxlibrary-0.1.0.1.dist-info/DESCRIPTION.rst
robotframework_xlsxlibrary-0.1.0.1.dist-info/METADATA
robotframework_xlsxlibrary-0.1.0.1.dist-info/RECORD
robotframework_xlsxlibrary-0.1.0.1.dist-info/WHEEL
robotframework_xlsxlibrary-0.1.0.1.dist-info/metadata.json
robotframework_xlsxlibrary-0.1.0.1.dist-info/top_level.txt
