Metadata-Version: 2.0
Name: robotframework-xlsxlibrary
Version: 0.1.0.1
Summary: Excel utility library for Robot Framework
Home-page: https://github.com/divfor/robotframework-xlsxlibrary
Author: AntZ
Author-email: divfor@gmail.com
License: UNKNOWN
Platform: UNKNOWN
Requires-Dist: openpyxl (>=2.3.0)
